k_math_kit/__init__.py
k_math_kit/integration.py
k_math_kit/polynomial/__init__.py
k_math_kit/polynomial/utils.py
k_math_kit/polynomial/newton_poly/__init__.py
k_math_kit/polynomial/newton_poly/newton_interpol_poly.py
k_math_kit/polynomial/newton_poly/newton_poly.py
k_math_kit/polynomial/newton_poly/spline1_poly.py
k_math_kit/polynomial/taylor_poly/__init__.py
k_math_kit/polynomial/taylor_poly/spline3_poly.py
k_math_kit/polynomial/taylor_poly/spline3_polys.py
k_math_kit/polynomial/taylor_poly/taylor_poly.py
k_math_kit-0.0.2.dist-info/METADATA
k_math_kit-0.0.2.dist-info/WHEEL
k_math_kit-0.0.2.dist-info/licenses/LICENSE
k_math_kit-0.0.2.dist-info/RECORD
