Metadata-Version: 2.3
Name: k_math_kit
Version: 0.0.2
Summary: A package with some usual math functions and objects, generally concerning numerical analysis
Project-URL: Homepage, https://pypi.org/project/k-math-kit/
Project-URL: Issues, https://github.com/KpihX/k_math_kit/issues
Project-URL: Repository, https://github.com/KpihX/k_math_kit.git
Author-email: KpihX <kapoivha@gmail.com>
Maintainer-email: KpihX <kapoivha@gmail.com>
License: MIT License
License-File: LICENSE
Keywords: analysis,integration,math,numerical,polynomial
Classifier: Development Status :: 4 - Beta
Classifier: Intended Audience :: Developers
Classifier: License :: OSI Approved :: MIT License
Classifier: Operating System :: OS Independent
Classifier: Programming Language :: Python :: 3
Requires-Python: >=3.8
